odoo/addons/mass_mailing_somconnexio/CHANGELOG.md
odoo/addons/mass_mailing_somconnexio/README.rst
odoo/addons/mass_mailing_somconnexio/__init__.py
odoo/addons/mass_mailing_somconnexio/__manifest__.py
odoo/addons/mass_mailing_somconnexio/controllers/__init__.py
odoo/addons/mass_mailing_somconnexio/controllers/controllers.py
odoo/addons/mass_mailing_somconnexio/data/mailing_list_data.xml
odoo/addons/mass_mailing_somconnexio/models/__init__.py
odoo/addons/mass_mailing_somconnexio/models/contract_contract.py
odoo/addons/mass_mailing_somconnexio/models/mass_mailing.py
odoo/addons/mass_mailing_somconnexio/tests/__init__.py
odoo/addons/mass_mailing_somconnexio/tests/models/__init__.py
odoo/addons/mass_mailing_somconnexio/tests/models/test_mass_mailing.py
odoo/addons/mass_mailing_somconnexio/tests/services/__init__.py
odoo/addons/mass_mailing_somconnexio/tests/services/test_mass_mailing_unsubscribe.py
odoo/addons/mass_mailing_somconnexio/tests/wizards/test_test_mailing.py
odoo/addons/mass_mailing_somconnexio/views/mail_mail_statistics_view.xml
odoo/addons/mass_mailing_somconnexio/views/mass_mailing_view.xml
odoo/addons/mass_mailing_somconnexio/views/menus.xml
odoo/addons/mass_mailing_somconnexio/wizards/__init__.py
odoo/addons/mass_mailing_somconnexio/wizards/test_mailing/__init__.py
odoo/addons/mass_mailing_somconnexio/wizards/test_mailing/test_mailing.py
odoo/addons/mass_mailing_somconnexio/wizards/test_mailing/test_mailing.xml
odoo_addon_mass_mailing_somconnexio-16.0.1.0.1.dist-info/METADATA
odoo_addon_mass_mailing_somconnexio-16.0.1.0.1.dist-info/WHEEL
odoo_addon_mass_mailing_somconnexio-16.0.1.0.1.dist-info/top_level.txt
odoo_addon_mass_mailing_somconnexio-16.0.1.0.1.dist-info/RECORD
