Metadata-Version: 2.1
Name: odoo-addon-mass-mailing-somconnexio
Version: 16.0.1.0.1
Summary: Odoo Som Connexió Mass Mailing customizations
Home-page: https://coopdevs.org
Author: Coopdevs Treball SCCL, Som Connexió SCCL
License: AGPL-3
Platform: UNKNOWN
Classifier: Programming Language :: Python
Classifier: Framework :: Odoo
Classifier: Framework :: Odoo :: 16.0
Classifier: License :: OSI Approved :: GNU Affero General Public License v3
Requires-Python: >=3.10
Requires-Dist: odoo-addon-cooperator-somconnexio <16.1dev,>=16.0dev
Requires-Dist: odoo-addon-mass-mailing-list-dynamic <16.1dev,>=16.0dev
Requires-Dist: odoo <16.1dev,>=16.0a
